sgr_refine_chain/__init__.py
sgr_refine_chain/agent.py
sgr_refine_chain/async_node.py
sgr_refine_chain/examples/langgraph_integration.py
sgr_refine_chain/examples/log_analysis.py
sgr_refine_chain-0.1.1.dist-info/LICENSE
sgr_refine_chain-0.1.1.dist-info/METADATA
sgr_refine_chain-0.1.1.dist-info/WHEEL
sgr_refine_chain-0.1.1.dist-info/RECORD
