Metadata-Version: 2.1
Name: sgr-refine-chain
Version: 0.1.1
Summary: Universal SGR Refine Agent for LangGraph — structured iterative refinement for large-context LLMs
Home-page: https://github.com/litvan007/sgr-refine-chain
License: MIT
Author: Ivan Litvinov
Author-email: litvan007@gmail.com
Requires-Python: >=3.13,<4.0
Classifier: License :: OSI Approved :: MIT License
Classifier: Programming Language :: Python :: 3
Classifier: Programming Language :: Python :: 3.13
Requires-Dist: langchain-core (>=1.0.4,<2.0.0)
Requires-Dist: langchain-openai (>=1.0.2,<2.0.0)
Requires-Dist: langgraph (>=1.0.3,<2.0.0)
Requires-Dist: pydantic (>=2.12.4,<3.0.0)
Project-URL: Repository, https://github.com/litvan007/sgr-refine-chain
